pytimeplot/__init__.py
pytimeplot/pytimeplot.py
pytimeplot-0.0.2.dist-info/LICENSE
pytimeplot-0.0.2.dist-info/METADATA
pytimeplot-0.0.2.dist-info/WHEEL
pytimeplot-0.0.2.dist-info/top_level.txt
pytimeplot-0.0.2.dist-info/RECORD
