Metadata-Version: 2.1
Name: pytimeplot
Version: 0.0.2
Summary: Function performance graphing library
Home-page: https://github.com/Evan-Hock/pytimeplot
Author: Evan Hock
Author-email: mocaointegral@gmail.com
Classifier: Programming Language :: Python :: 3.10
Classifier: License :: OSI Approved :: GNU General Public License v3 (GPLv3)
Classifier: Operating System :: OS Independent
Requires-Python: >=3.10
License-File: LICENSE
Requires-Dist: pycombinators
Requires-Dist: matplotlib
Requires-Dist: pandas
